datareuse/__init__.py
datareuse/reuse.py
tests/__init__.py
tests/test_reuse.py
datareuse-0.0.3.dist-info/LICENSE
datareuse-0.0.3.dist-info/METADATA
datareuse-0.0.3.dist-info/WHEEL
datareuse-0.0.3.dist-info/top_level.txt
datareuse-0.0.3.dist-info/RECORD
